_core_pybinds.cpython-311-x86_64-linux-gnu.so
_ase_pybinds.cpython-311-x86_64-linux-gnu.so
_aea_pybinds.cpython-311-x86_64-linux-gnu.so
_adt_pybinds.cpython-311-x86_64-linux-gnu.so
projectaria_tools.libs/libavutil-a5e84e69.so.59.39.100
projectaria_tools.libs/libxxhash-5b835a6a.so.0.8.2
projectaria_tools.libs/libavformat-0adaa0c2.so.61.7.100
projectaria_tools.libs/libboost_filesystem-0ad33d61.so.1.84.0
projectaria_tools.libs/libzstd-8d126cbb.so.1.5.5
projectaria_tools.libs/libboost_atomic-25f80f16.so.1.84.0
projectaria_tools.libs/libdrm-827b956f.so.2.4.0
projectaria_tools.libs/libpng15-ce838cd1.so.15.13.0
projectaria_tools.libs/libopus-63eb2747.so.0.10.1
projectaria_tools.libs/libturbojpeg-e493a927.so.0.3.0
projectaria_tools.libs/liblz4-af1653fb.so.1.8.3
projectaria_tools.libs/libboost_date_time-051606fe.so.1.84.0
projectaria_tools.libs/libboost_iostreams-f403082f.so.1.84.0
projectaria_tools.libs/libavcodec-c81c96af.so.61.19.100
projectaria_tools.libs/libjpeg-6583d9b9.so.8.3.2
projectaria_tools/__init__.py
projectaria_tools/__init__.pyi
projectaria_tools/projects/adt.pyi
projectaria_tools/projects/__init__.py
projectaria_tools/projects/aea.pyi
projectaria_tools/projects/ase.pyi
projectaria_tools/projects/dtc_objects/__init__.py
projectaria_tools/projects/dtc_objects/downloader_lib.py
projectaria_tools/projects/dtc_objects/downloader_main.py
projectaria_tools/projects/ase/__init__.py
projectaria_tools/projects/ase/readers.py
projectaria_tools/projects/ase/interpreter.py
projectaria_tools/projects/adt/__init__.py
projectaria_tools/projects/adt/utils.py
projectaria_tools/projects/aea/__init__.py
projectaria_tools/utils/__init__.py
projectaria_tools/utils/calibration_utils.py
projectaria_tools/utils/rerun_helpers.py
projectaria_tools/core/sensor_data.py
projectaria_tools/core/data_provider.pyi
projectaria_tools/core/__init__.py
projectaria_tools/core/sophus.py
projectaria_tools/core/xprs.py
projectaria_tools/core/image.py
projectaria_tools-2.1.0.dist-info/RECORD
projectaria_tools-2.1.0.dist-info/entry_points.txt
projectaria_tools-2.1.0.dist-info/WHEEL
projectaria_tools-2.1.0.dist-info/top_level.txt
projectaria_tools-2.1.0.dist-info/METADATA
projectaria_tools-2.1.0.dist-info/licenses/LICENSE
