Metadata-Version: 2.4
Name: projectaria-tools
Version: 2.1.0
Summary: Project Aria Tools
Home-page: https://github.com/facebookresearch/projectaria_tools
Author: Meta Reality Labs Research
License: Apache-2.0
Requires-Python: >=3.8
License-File: LICENSE
Requires-Dist: numpy
Requires-Dist: requests
Requires-Dist: rerun-sdk==0.22.1
Requires-Dist: tqdm
Provides-Extra: all
Requires-Dist: jupyter; extra == "all"
Requires-Dist: matplotlib; extra == "all"
Requires-Dist: pandas; extra == "all"
Requires-Dist: pillow; extra == "all"
Requires-Dist: plotly; extra == "all"
Requires-Dist: scipy; extra == "all"
Requires-Dist: rerun-notebook==0.22.1; extra == "all"
Requires-Dist: moviepy==1.0.3; extra == "all"
Dynamic: author
Dynamic: description
Dynamic: home-page
Dynamic: license
Dynamic: license-file
Dynamic: provides-extra
Dynamic: requires-dist
Dynamic: requires-python
Dynamic: summary
